odoo/addons/mail_activity_unlink_log/README.rst
odoo/addons/mail_activity_unlink_log/__init__.py
odoo/addons/mail_activity_unlink_log/__manifest__.py
odoo/addons/mail_activity_unlink_log/data/unlink_message.xml
odoo/addons/mail_activity_unlink_log/i18n/es.po
odoo/addons/mail_activity_unlink_log/i18n/it.po
odoo/addons/mail_activity_unlink_log/i18n/mail_activity_unlink_log.pot
odoo/addons/mail_activity_unlink_log/models/__init__.py
odoo/addons/mail_activity_unlink_log/models/mail_activity.py
odoo/addons/mail_activity_unlink_log/readme/CONTRIBUTORS.rst
odoo/addons/mail_activity_unlink_log/readme/DESCRIPTION.rst
odoo/addons/mail_activity_unlink_log/static/description/icon.png
odoo/addons/mail_activity_unlink_log/static/description/index.html
odoo/addons/mail_activity_unlink_log/tests/__init__.py
odoo/addons/mail_activity_unlink_log/tests/test_activity_unlink.py
odoo14_addon_mail_activity_unlink_log-14.0.1.0.1.dev7.dist-info/METADATA
odoo14_addon_mail_activity_unlink_log-14.0.1.0.1.dev7.dist-info/WHEEL
odoo14_addon_mail_activity_unlink_log-14.0.1.0.1.dev7.dist-info/top_level.txt
odoo14_addon_mail_activity_unlink_log-14.0.1.0.1.dev7.dist-info/RECORD
